<?xml version="1.0" encoding="UTF-8" standalone="no"?>
<pk><wd nm="cea" rd="341,0:731,759,770"/><wd nm="cean" rd="300,0:526"/><wd nm="ceana" rd="277,0:1299"/><wd nm="ceania" rd="85,0:392,1068,1076,1093,10584,33787|89,0:58199,59527,70488,85436,85444,95853|319,128:0,28,65,84,117,641|422,0:357|423,0:441|451,0:2393|452,0:2602,4946|476,0:2798,5223"/><wd nm="ceara" rd="85,0:25148,25154,25169|89,0:105848,105854|145,0:335"/><wd nm="ceatharlach" rd="237,0:256"/><wd nm="ceava" rd="341,0:689"/><wd nm="cebu" rd="332,0:697"/><wd nm="cecharts" rd="30,0:3951|31,0:3203|33,0:4341,7281,10396|45,0:5452,5588,5638,5716,5870|51,0:500,2044,5744,6202,7245"/><wd nm="cecil" rd="272,0:419"/><wd nm="cecode" rd="82,0:3815"/><wd nm="ced" rd="0,0:4151,5591|4,0:2401,2718,2841,3142,3209,3376,3873,4007,4132,4190,4301,4355,4397,4498,4558,4607,4645,4950,5045,5087,5350,5380,5464|8,0:932|13,0:11039,11310,11475,11643,12187,12586,12883,13019,13124,13250,28166,33240|14,0:1173|15,128:0,25,94,7448,7745,9840|16,0:284,332|17,0:1098,1213,1765,1814,1964,7848|18,0:2721|21,0:646,786|23,0:87,6286,6468,9094|30,0:2953,3199,3448|32,0:946|33,0:353,455,1496,1742,1988,6234,6480,6726|34,0:2051|35,0:3076,3537,5599,5845,6091|36,0:775|37,0:366,465,3267,6898|46,0:2159,5742,6154,6964,8142|47,0:3222|56,0:721,13763|60,0:2625|62,0:1016|63,0:3348,6532|64,0:1906,4848|65,0:852,4704,7399,7446|67,0:2556,9236|68,0:6375|73,0:1794|74,0:1587|77,0:158|79,0:4417,4523|81,0:1332|83,0:1685|89,0:361,1310,2700,3214,10205,10540,12439,20616,26402,26729,26853,27150,27217,27384,27881,28015,28140,28198,28309,28363,28405,28506,28566,28615,28653,28958,29053,29095,29358,29388,29472,29823,35059,37195,38486,40504,49512,57608,57657,58039,58131,58492,58519,58589,59152,59449,80792,84866|90,0:204,1168,1590,1714,1780|91,0:290,470,720,784,1386,1477,1826,2368,2710,3018,3080,3706,3768,4384,5005,5447,5992,6480,7007,7557,7954,8420,8770,9379,10538,11638,12357,12595,12883,13238,13588,14390,14984,15588,15956,16924,17887,18861,19230,19594,20143,20994|92,0:4479,21776|93,0:359,2368|98,0:2147,4122|100,0:427,1128,1168|101,0:1259,2324,4339,6265,8141,9026,10029,11017,12274|102,0:2880,4816,4880|103,0:87,6262,6444,9213|104,0:210,718,905,1727|105,0:130,772,3159,3232,3925,4123|106,0:1181|107,0:643,9909|108,0:1539|153,0:678|432,0:3451|434,0:640,2514,3251,6289|436,0:3671|438,0:7513|443,0:1553|452,0:8035|460,0:1565,11231|468,0:1471,10862|476,0:8162"/><wd nm="ced9" rd="432,0:720"/><wd nm="cedar" rd="234,0:461|282,0:571|292,0:436"/><wd nm="cedecimals" rd="4,0:1214|95,0:3257"/><wd nm="cedepartment" rd="85,0:4295,4321|89,0:88968|208,0:111,153"/><wd nm="cedepartmentmap" rd="208,0:83"/><wd nm="cedo" rd="187,0:687"/><wd nm="cedonia" rd="85,0:4802,4812,4831|89,0:89467,89477|199,0:620|200,0:688|202,0:685|215,0:290,322,470|262,128:0,30,69,90,125,1822|368,0:405|426,0:2683"/><wd nm="cedure" rd="41,0:2353|446,0:400|450,0:297|454,0:414|458,0:301|462,0:417|466,0:304|470,0:391|474,0:296"/><wd nm="ceed" rd="57,0:3129|80,0:706|446,0:2279|454,0:3958|462,0:3534|470,0:1950"/><wd nm="ceeding" rd="451,0:382|453,0:597|459,0:389|460,0:1034|461,0:623|467,0:392|469,0:627|475,0:381|477,0:613"/><wd nm="ceeds" rd="105,0:4541"/><wd nm="ceedwardisland" rd="85,0:8705,8733|89,0:93589|336,0:87,117,161"/><wd nm="cefully" rd="4,0:1063"/><wd nm="ceg" rd="287,0:376"/><wd nm="cegovačka" rd="143,0:519"/><wd nm="cegovačko" rd="143,0:326"/><wd nm="ceh" rd="233,0:263"/><wd nm="ceiba" rd="337,0:537"/><wd nm="ceima" rd="288,0:670"/><wd nm="ceive" rd="21,0:901|56,0:13214"/><wd nm="ceived" rd="102,0:2570|433,0:1903,2056"/><wd nm="ceives" rd="102,0:4186"/><wd nm="ceiving" rd="15,0:9198|47,0:1910"/><wd nm="cel" rd="57,0:469|91,0:4721,5856,6829"/><wd nm="celand" rd="85,0:4490,4498,4515|89,0:89178,89186|199,0:507|200,0:553|202,0:572|228,128:0,28,65,84,117,934|311,0:355|426,0:2570"/><wd nm="celdataload" rd="91,0:5813"/><wd nm="celdataloadrequest" rd="89,0:53039|91,0:4671,4843"/><wd nm="celdataupdate" rd="91,0:6781"/><wd nm="celeration" rd="438,0:6760,6774,6984,6999"/><wd nm="celi" rd="392,0:1307"/><wd nm="cell" rd="79,0:3676"/><wd nm="celled" rd="89,0:52958,53021,53233,53288|91,0:4749,4825,5884,5952|92,0:3879,3904,10449,10474|93,0:2418,2468"/><wd nm="cellpadding" rd="68,0:2383,4994"/><wd nm="cells" rd="76,0:4154"/><wd nm="cellspacing" rd="68,0:2370,4981"/><wd nm="celona" rd="372,0:409"/><wd nm="celoneta" rd="337,0:390"/><wd nm="cement" rd="89,0:56128,56764|90,0:6675"/><wd nm="cements" rd="89,0:2812|90,0:80"/><wd nm="cen" rd="118,0:1050"/><wd nm="cenario" rd="4,0:4269,4474,4914,5314|23,0:560,15230|64,0:4129|67,0:531|89,0:28277,28482,28922,29322|103,0:526,15456"/><wd nm="cenarios" rd="23,0:806|31,0:245|46,0:3166|67,0:789|103,0:724"/><wd nm="cendant" rd="23,0:284,408,425,1045,1102,1197,1676,2190,2476,3376,6551,6621,8102,8431,8473,8638,8680,8716,8784,8916,12226,12345,12482,13397,14002,14251|67,0:274,379,396,1201,1253,1351,2002,2334,8719|103,0:276,374,391,964,1021,1119,1599,2043,2152,2293,2351,2388,2430,2472,3352,6527,6597,8078,8407,8449,8614,8656,8835,8903,9035,12338,12460,12593,13371,14339,16212,16281,16353,16420"/><wd nm="cendent" rd="23,0:2400,6742|67,0:2188|103,0:6718"/><wd nm="cenes" rd="18,0:93|46,0:6777|63,0:2789|64,0:1310"/><wd nm="cense" rd="57,0:3413,3537,3603|82,0:125,3753|88,0:204,425|90,0:5454"/><wd nm="censed" rd="70,0:980|73,0:2389|74,0:2201|85,0:13420,24257,26722,32328,33801,35064"/><wd nm="censes" rd="57,0:3438"/><wd nm="cension" rd="259,0:323"/><wd nm="census" rd="86,0:194"/><wd nm="cent" rd="9,0:1792,1817,2457,2549|10,0:2828,2882,2918,3113|15,0:1896|58,0:1203|65,0:6094,6224|85,0:7064|89,0:7430,7450,91850|95,0:4243,4664|161,0:691|162,0:643|307,0:668|346,128:5,54,112,560|426,0:613|446,0:7107|454,0:8611|462,0:8285|470,0:6320"/><wd nm="centa" rd="219,0:657"/><wd nm="centage" rd="14,0:1152|15,0:1874|58,0:153,378,1265,1441,2481|71,0:3929,4071|79,0:4814|89,0:7649,51437|92,0:17753|94,0:2606,3056|106,0:2408,2561,10168,10321|107,0:1339,1492|109,0:3953,4109|110,0:2728,2884,6896|446,0:3021,3144,5030,5075,5533,5820,5943,6185,6228,6362,6424|447,0:382,493|448,0:97,585,1234,1255|450,0:5445,5774,6360|454,0:4726,6616,6661,7156,7423,7818,7861,7995,8057|455,0:389,500|456,0:104,592,1241,1262|458,0:8448,8782,10341|462,0:4323,6339,6384,6879,7137,7563,7606,7740,7802|463,0:392,503|464,0:107,595,1244,1265|466,0:7867,8202,9733|470,0:2497,4432,4477,4932,5093,5406,5449,5584,5646|471,0:378,489|472,0:97,582,1227,1248|474,0:2647,5695,6040,6631"/><wd nm="centages" rd="448,0:741|456,0:748|464,0:751|472,0:737"/><wd nm="centandthegrenadines" rd="85,0:7088,7126|89,0:91874|346,0:147,201"/><wd nm="centar" rd="262,0:441,456"/><wd nm="cente" rd="157,0:485|192,0:445"/><wd nm="cented" rd="15,0:7030,8281,8444"/><wd nm="center" rd="0,0:5444,5648,5680,6005,6077|13,0:4436,4632,7197,7511,7543,7936,8298,28399,28485,29713,33151|18,0:1995|21,0:2306|28,0:562,1064,1143,1150|30,0:2904,3150,3399,3723|33,0:1447,1693,1939,3009,6185,6431,6677,7002,10046|34,0:2002,2240|35,0:3027,3275,3488,3738,5550,5796,6042,6289|37,0:1658,3218,3548,7400|38,0:838|56,0:13714|89,0:19984,20196,20540,20572,21736,30210,30239,31369,31684,31716,32082|95,0:1678,2152|101,0:14724,15308|433,0:419,995|434,0:1240,1315,6200|435,0:215,2240|436,0:638,3979|438,0:3984,5262,5300,5702,5741|441,0:1736|453,0:2790|476,0:1829,4112|477,0:1625,3358"/><wd nm="centerx" rd="438,0:5249,5688,6056"/><wd nm="centery" rd="438,0:5287,5727,6138"/><wd nm="central" rd="78,0:382|85,0:870,1154,1163,1195,3185,5984,7782,7797,7892,11492,14044,20256,20310,28384,32561,43199,43268,43628,43697|89,0:60868,60922,65142,69253,79755,79824,80184,80253,85219,85536,85545,87800,90709,92640,92655,92736,96875|90,0:5942,5989|113,0:401|117,0:262|133,0:332,351,371|134,0:270|144,0:289|146,0:278|147,0:375,394,416|159,0:0,43,95|160,0:0,35,79|161,0:0,36,81|162,0:0,49,107|163,0:0,42,93|201,0:358|211,0:313|214,0:308|215,0:263,283|225,0:289|227,0:290,313|233,0:335,353,377|238,0:251|246,0:243|270,0:260|298,0:360|308,0:19,66,122,138,186|328,0:333|329,0:400|350,0:286,388|353,0:300|355,0:327|356,0:364|359,0:265|362,0:315|370,0:270|374,0:289|383,0:681|402,0:3,40,86|405,0:349|422,0:336|423,0:420|426,0:1024|430,0:279|431,0:351|433,0:1761|445,0:2011|451,0:2313|452,0:2522,4866|476,0:2722,5147"/><wd nm="central_bohemian" rd="89,0:99512"/><wd nm="centralafrica" rd="85,0:32575,32598|89,0:69267,69290"/><wd nm="centralafricanrepublic" rd="85,0:11515,11547|89,0:96898|159,0:129,177"/><wd nm="centralamerica" rd="85,0:885,909|89,0:85234|160,0:105,145"/><wd nm="centralamerica2" rd="85,0:7926,7951|89,0:92770|161,0:108,149"/><wd nm="centralamericawithcaribbean" rd="85,0:7827,7864|89,0:92685"/><wd nm="centralamericawithcaribbeans" rd="162,0:147,201"/><wd nm="centralasia" rd="85,0:28396,28417|89,0:65154,65175"/><wd nm="centralbohemianregion" rd="85,0:14060,14091|89,0:99529"/><wd nm="centraldma" rd="85,0:43219,43248,43288,43317,43648,43677,43717,43746|89,0:79775,79804,79844,79873,80204,80233,80273,80302"/><wd nm="centraleuropeanregion" rd="85,0:6006,6037|89,0:90731|163,0:126,173"/><wd nm="centralhungary" rd="85,0:20271,20295|89,0:60883,60907"/><wd nm="centralize" rd="32,0:1017|36,0:846"/><wd nm="centrally" rd="13,0:33395|51,0:1082,4624|434,0:6444"/><wd nm="centralregion" rd="85,0:3199,3225|89,0:87814|402,0:111,153"/><wd nm="centraltransdanubia" rd="85,0:20330,20359|89,0:60942,60971"/><wd nm="centrate" rd="434,0:3197"/><wd nm="centre" rd="155,0:307|207,0:345|222,0:262|330,0:467|339,0:337|388,0:268"/><wd nm="centro" rd="195,0:381"/><wd nm="centru" rd="85,0:21852,21859,21875|89,0:62464,62471,62487"/><wd nm="ceo" rd="81,0:6531|434,0:2223"/><wd nm="ceola" rd="206,0:1145|234,0:1278|277,0:1344"/><wd nm="cepci" rd="329,0:414"/><wd nm="cept" rd="41,0:2399|43,0:456,2371|46,0:691,1160,2491,4860|53,0:492|55,0:1014|60,0:2538|62,0:1150|63,0:9616|66,0:78|76,0:2250|77,0:1254|88,0:275|89,0:7408,15947,48093|91,0:381|92,0:16283|101,0:13687|107,0:8078|110,0:5283,5431|433,0:45,2928|438,0:1959|445,0:48|453,0:276|461,0:295|469,0:298|477,0:292"/><wd nm="ceptable" rd="71,0:3515,4444,4672|89,0:30132|106,0:1881,1999,2942,3217,7416,8162,9759,10702,10977|107,0:1873,2147|109,0:3547,4490,4764|110,0:2236,2376,3265,3540"/><wd nm="cepted" rd="51,0:7826|106,0:7324,8066"/><wd nm="cepting" rd="89,0:16144"/><wd nm="ception" rd="17,0:8432,8446,8466,8490,8509,8543|45,0:2446|83,0:2344|91,0:3298,3314,3336,3362,3383,3986,4002,4024,4050,4071|458,0:13124,13552|466,0:12681"/></pk>