<?xml version="1.0" encoding="UTF-8" standalone="no"?>
<pk><wd nm="tity&apos;s" rd="76,0:3888|78,0:685,707|460,0:6834|468,0:6307"/><wd nm="tity_id" rd="446,0:2067,2137,2374,2500,2562,2577,3479,3562,3578,4758,4837,4907,5190,5316,5378,5393,6846,6929,6945,7049|449,0:2114|454,0:3746,3816,4272,4398,4478,4501,5253,5275,5379,6423,6493,6777,6903,6983,7006,8358,8380,8484,8552|457,0:2133|462,0:3330,3400,3883,4009,4089,4112,4892,4914,4961,6067,6146,6216,6500,6626,6706,6729,8068,8090,8137,8226|465,0:2136|470,0:1746,1814,2064,2188,2251,2267,2902,2959,2976,4149,4239,4307,4604,4728,4791,4807,6058,6115,6132,6255|473,0:2170"/><wd nm="tityalpha" rd="13,0:9584|89,0:32192"/><wd nm="titycolor" rd="13,0:9478|89,0:32095"/><wd nm="titydef" rd="13,0:34543,34749,34766,34844,34882|77,0:1380,1642,2090"/><wd nm="tityrollout" rd="89,0:12923,52300|91,0:14882|93,0:2621|101,0:601,12175,12194,12831,13373"/><wd nm="tityrollover" rd="89,0:12878,52236|91,0:14287|93,0:2606|101,0:556,10917,10937,11582,12116"/><wd nm="titytooltip" rd="13,0:9690|89,0:30794"/><wd nm="tius" rd="85,0:12467,12477,12496,26497,26507,26531|89,0:97952,97962,107300,107310|113,0:1272|275,128:0,30,69,90,125,555|426,0:1721"/><wd nm="tivar" rd="262,0:737"/><wd nm="tivat" rd="287,0:529"/><wd nm="tivate" rd="18,0:343|446,0:1002|450,0:683|474,0:734|477,0:1394"/><wd nm="tivated" rd="17,0:3546,3729|100,0:3056,3242"/><wd nm="tive" rd="0,0:508,1948,2062,2318|1,0:2644|4,0:5662,5711|8,0:209|10,0:1582|13,0:27994,28034,35121,35168|14,0:583,1853,1958|15,0:1655,1698,2144,4617,8069|16,0:1335|17,0:4887,6604,6753,6886|18,0:1819|22,0:10031|23,0:700,15427,15634|24,0:11548|25,0:878,1084,1308,1626|31,0:2000|35,0:4436|37,0:9382,9492|40,0:287|42,0:1681|44,0:2183|50,0:1683|51,0:2741|53,0:923,1427|54,0:287|56,0:5613,8503,9453|58,0:185,300|63,0:9178,9982|64,0:3914,4069,4628|65,0:2300,2986|67,0:696|68,0:4475,4514,5967|72,0:5580|73,0:787|76,0:4101|79,0:3598,4106|80,0:409|82,0:3640|84,0:815|85,0:250,9208|86,0:129,771|89,0:3438,4035,5207,7038,9898,10035,17383,17573,17881,18060,19528,29671,29720,39463,43795,44498,45225,51540,51602,55471,55602,57290,94142|90,0:1481,1508,1545,2522,3674,5776|91,0:14620,14796,15214,15390,16484,17452,18415,19995,20845|92,0:10722,11221,11989,19439,19496,19558,22467,22512,22543,22626,22666,22682,22727,22799,22927|93,0:2288|95,0:588,1088|97,0:517,1708,1818,2350|98,0:2621|100,0:251,774,910,4403|101,0:925,2827,4842,6768,11185,11361,12442,12618|103,0:626,15653,15887|104,0:1317,1441|105,0:729,1535|107,0:1040,8176|110,0:778,6913,10599|167,128:51,145,248,1184|216,0:184|313,0:189|328,0:209|339,0:169|369,0:189|433,0:2246|435,0:2124|436,0:3449,3517|438,0:5784|441,0:3741|443,0:4226|449,0:2524|451,0:3978|452,0:4244|457,0:2543|459,0:5149|465,0:2547|467,0:4943|473,0:2595|475,0:3692|476,0:2323,4547,4748"/><wd nm="tiveanimation" rd="13,0:15491|89,0:32715"/><wd nm="tiveanimduration" rd="13,0:15645|89,0:32860"/><wd nm="tivelegend" rd="13,0:13946|89,0:17906,33021"/><wd nm="tively" rd="1,0:998|10,0:1643,2232,2306|18,0:3105|33,0:2232,4127,9314|35,0:1444|51,0:3724|60,0:2404|73,0:1062|74,0:941|76,0:213|86,0:286|89,0:39114|92,0:20284|103,0:19284,29541|436,0:3324|438,0:2650|443,0:788|452,0:74|460,0:81|468,0:84|476,0:74"/><wd nm="tivetab" rd="103,0:28210,30154"/><wd nm="tivex" rd="57,0:257,349"/><wd nm="tivities" rd="17,0:333,578|100,0:1676"/><wd nm="tivity" rd="13,0:15592,15758|17,0:2138|63,0:207|64,0:302|76,0:4053|79,0:3540|89,0:32807,32962,39547,40612|90,0:746"/><wd nm="tiyah" rd="253,0:290"/><wd nm="tizi" rd="118,0:1032"/><wd nm="tičko" rd="175,0:622"/><wd nm="tj" rd="126,0:784|167,0:895,898|337,0:1315|369,0:351|382,0:292,316,332,373|426,0:2179"/><wd nm="tje" rd="271,0:787"/><wd nm="tjoly" rd="209,0:610"/><wd nm="tjozondjupa" rd="290,0:472"/><wd nm="tjs" rd="23,0:15818|103,0:2492,27431,28061,28389,28456,28981,29605,29636,29699,29766,29885,29906,29957,30005,30715"/><wd nm="tjsinstance" rd="92,0:22452,23841|94,0:2337,2498,2946,3394"/><wd nm="tjsobj" rd="98,0:966"/><wd nm="tjsondata" rd="66,0:1814,2859,2900,3361|74,0:1844|89,0:9808,16175,16285,44883,44915,50840|92,0:11369,11397,11654,11773,14158,14240|93,0:2029,2153|96,0:2023,2104,2181,3009,7317,7431|98,0:890|99,0:2410,2684,2767"/><wd nm="tjsonurl" rd="2,0:251|15,0:5309|66,0:789,2191|73,0:2017|89,0:9797,16164,16259,44431,44772|92,0:11142,11339|93,0:2018|96,0:1719,1758,2908,7090|98,0:902"/><wd nm="tjylland" rd="85,0:20062,20074,20095|89,0:60674,60686,60707|183,0:332"/><wd nm="tk" rd="199,0:950|200,0:1036,1039|202,0:994|241,0:863|368,0:503|386,0:1476,1479|409,0:485,488|426,0:3013"/><wd nm="tka" rd="115,0:733|342,0:439,652"/><wd nm="tken" rd="250,0:300"/><wd nm="tki" rd="303,0:455"/><wd nm="tkin" rd="169,0:1013|280,0:263"/><wd nm="tkinson" rd="212,0:274"/><wd nm="tkittsandnevis" rd="85,0:6970,6998|89,0:91758|344,0:117,161"/><wd nm="tl" rd="13,0:8192,8241|63,0:13613|64,0:6588|114,0:1328|118,0:1044,1047|168,0:304,308|189,0:287,301,316,331,346,363,381,394,409,424,440,457,474|192,0:320|204,0:523,526|212,0:2607|224,0:260|250,0:398,401|262,0:337,340|263,0:410,413|264,0:421,438,454,679|276,0:814|303,0:408,438|304,0:515,553|305,0:359,362|341,0:728|342,0:1446,1449|344,0:591"/><wd nm="tla" rd="218,0:355"/><wd nm="tlabel" rd="13,0:35768|79,0:537,771,2528,2931,3020|89,0:18863,19102,19336,34815|91,0:14853,15447|101,0:11418,12675"/><wd nm="tland" rd="85,0:5293,5302,5320,6287,16436,16445,16463,16652,16665,16687|89,0:82984,90017,90026,91002,102066,102075,102312,102325|90,0:2560,2569|193,0:1093|202,0:1025|240,0:314|282,0:1722|286,0:1151|302,0:459|309,0:1546|352,128:0,29,67,87,121,267,1011|353,128:0,35,79,539|378,0:301,335,443|385,0:1302|397,0:250|398,0:258|413,0:412"/><wd nm="tlandregion" rd="85,0:6304,6328|89,0:91019|353,0:105,145"/><wd nm="tlanta" rd="432,0:1229,1958,2143|437,0:1123"/><wd nm="tlantic" rd="85,0:43337,43538|89,0:79893,80094|300,0:266"/><wd nm="tlanticdma" rd="85,0:43355,43382,43555,43581|89,0:79911,79938,80111,80137"/><wd nm="tlantique" rd="140,0:307|208,0:1274"/><wd nm="tlantiques" rd="208,0:1594"/><wd nm="tlaxcala" rd="276,0:818"/><wd nm="tle" rd="3,0:113|17,0:7126,7174|20,0:1580,1620|21,0:2116,2138|23,0:2693,2733|33,0:11934,11983,12045,12118|37,0:5319,8820,8869,8930,9347|38,0:2128,2177,2238|40,0:692|41,0:3123,3134|49,0:2776,2919,4111,4135,4163,4189|54,0:692|58,0:757,801,1396,1452,2975,3037|60,0:663,726|63,0:2030,2078,7574,7622,11230,11278|64,0:689,733,3097,3141,4159,4203|65,0:1130,1199,3386,3455|66,0:543,588,1571,1613|67,0:1552,1592|68,0:2249,2289,4612,4652|69,0:1075,1121,2797,2843|71,0:2472,2505|72,0:933,981,1701,1749,3322,3370,4076,4124,5101,5149|85,0:38114|89,0:4759,4775,5637,5685,6571,6602,8107,8152,11225,11269,11701,11736,30012,30051,30105,30119,74670|90,0:2821,2833,2893|95,0:1587,1606|96,0:586,619,5788,5810|97,0:1270,1318|98,0:1297,1330|99,0:1338,1357,3240,3267,5492,5519|101,0:1565,1614,3545,3594,5559,5605,7411,7456,8363,8411,9251,9300,10238,10286,11556,11602,12805,12850,14265,14315|102,0:1371,1415,3446,3490|103,0:2669,2709,18132,19569,20998,22836,24706,26460|105,0:1694,1724|106,0:1240,1273|109,0:2548,2579|110,0:8141,8979,9183|124,0:854|158,0:388|180,0:279|245,0:1735|385,0:1056|432,0:926,1850,2045,2442,2551|435,0:3439|437,0:810|446,0:854,888|450,0:535,569|451,0:815,877|453,0:1241,1289|454,0:645,679|458,0:582,616|459,0:774,833|460,0:3271,3333|461,0:1037,1072|462,0:648,682|466,0:585,619|467,0:783,842|468,0:3193,3255|469,0:1116,1151|470,0:857,891|474,0:583,617|475,0:653,682|476,0:1487,1553|477,0:1207,1255"/><wd nm="tleareacode" rd="85,0:38130,38155|89,0:74686,74711"/><wd nm="tled" rd="435,0:3866"/><wd nm="tlemcen" rd="118,0:1050"/><wd nm="tlen" rd="212,0:2694"/><wd nm="tleng" rd="144,0:338"/><wd nm="tlength" rd="459,0:4458|460,0:5894,8790|461,0:3647"/><wd nm="tler" rd="114,0:360|234,0:405|243,0:373|245,0:473|282,0:449|292,0:410|320,0:381|330,0:409"/><wd nm="tlereagh" rd="312,0:413"/><wd nm="tles" rd="33,0:12297|38,0:445|95,0:459|107,0:7261|110,0:613"/><wd nm="tley" rd="212,0:463|232,0:1578|245,0:1965|385,0:1860,2939"/><wd nm="tli" rd="128,0:352,456"/><wd nm="tline" rd="442,0:66"/><wd nm="tlines" rd="82,0:3875"/><wd nm="tlinetype" rd="103,0:24185,26597"/><wd nm="tlis" rd="392,0:516"/><wd nm="tlistener" rd="17,0:5432,5557,5685,5806,8067|89,0:10242,10580,11000,11066,11625,12010,15066,37160,37325,37382,37521,37626,37696,37900,49477,49642,49699,49838,49943,50013,50217,52123,52150,55752,55926|92,0:4360,4412,4640,5032,5087,5163,5238,5293,5430,5499,5704,5834|93,0:1447,1500,1922,1939,2351|100,0:4944,5069,5197,5318|101,0:1882,2095,2130,3862,4165,4196,5936,6096,6128,7794,7959,7990,8679,8834,8868,9637,9842,9877,10627,10839,10873,11939,12099,12131,13191,13356,13387|102,0:825,2990,3758,3875,3905,4063,4122,4152,4402,4609|103,0:16469,16586,17018,17140,17306,18604,20122,21472,23475,25058,27155,27213,28860,30776|104,0:752|105,0:2035"/><wd nm="tlon" rd="382,0:324"/><wd nm="tlong" rd="254,0:387"/><wd nm="tlowerbound" rd="467,0:4237|468,0:5514,8301"/><wd nm="tlucia" rd="85,0:7028,7048|89,0:91811|345,0:93,129"/><wd nm="tly" rd="4,0:891,1680,6534|5,0:157|8,0:510|10,0:61,1506|12,0:3174|13,0:9915,10148,15896,16023,30565,33320|15,0:561,5555,5840,7231,8492,8675,8844,8877,9346|16,0:2027|17,0:1738|20,0:2099|31,0:399,949|35,0:4506|42,0:715,2167,2204|44,0:2433,2730|45,0:168,2342|46,0:1044|47,0:2364,3087,3112,3359|55,0:573|56,0:1715,5881|57,128:0,481,1567,1642,3839,4128|58,0:2721|60,0:178|62,0:560,1447,4427,4475|64,0:2493,3856,4655|68,0:3887,3908,6009,6474|70,0:789,1015|71,0:5907,6814|72,0:2457,2932,2998|73,0:2424|74,0:2236|75,0:1234|79,0:4309|80,0:2972,3104,3711,4552|85,0:24|86,0:868,1456,3366|87,0:499|89,0:8850,14055,14543,34366,36130,42093,45988,55139|90,0:5315,6262,6618|91,0:4612,5232,5705,6217,13822,14096|92,0:1785,4842,7176,12576,21749|95,0:4045|96,0:4652|101,0:13873|102,0:2578|105,0:594,3629|106,0:4459,12219|107,0:1137,3391,10272|109,0:1701,6006,7120|110,0:4782|433,0:1603,2949|434,0:3802,6369|435,0:3675|438,0:3089,5938,6618|460,0:1747|461,0:2195|468,0:1653|469,0:2035|477,0:2346"/><wd nm="tlı" rd="132,0:876"/><wd nm="tm" rd="118,0:924,927|122,0:615|126,0:824|141,0:532,535|212,0:2657|225,0:508,511|226,0:489|256,0:796,799|263,0:392,395|264,0:327,398,509|276,0:793|334,0:2404,4749|341,0:716|344,0:616|393,0:302,315,330,347,361|426,0:2213"/><wd nm="tman" rd="212,0:2301|281,0:1158|392,0:462|417,0:941"/><wd nm="tmanager" rd="17,0:4020|89,0:9666,14224,14437,15841,38454,38467,39017|91,0:1579|92,0:19904,20187,20464,20772,20966,21115|93,0:1609|94,0:863|100,0:3042,3228,3408,3536,3597|104,0:1001,3799|105,0:1882,2277,2435,2554,4055|452,0:9239|460,0:12418|468,0:12049|476,0:9156"/></pk>