<?xml version="1.0" encoding="UTF-8" standalone="no"?>
<pk><wd nm="mple2" rd="35,0:3669"/><wd nm="mple_dataurl" rd="459,0:737,1623|467,0:746,1395"/><wd nm="mple_dataxml" rd="460,0:3234,4109|468,0:3156,3797"/><wd nm="mple_drilldown" rd="458,0:541,1249|466,0:544,1012"/><wd nm="mpleexample" rd="35,0:3208|37,0:3410"/><wd nm="mpleexample2" rd="35,0:3669"/><wd nm="mplement" rd="0,0:2959|8,0:2641|23,0:6878|33,0:936|37,0:911|44,0:147|66,0:317|72,0:501|76,0:2228|102,0:2061|103,0:6854"/><wd nm="mplementation" rd="15,0:3126,3429,9123|23,0:1949,5584,9131|42,0:2304|47,0:1835|62,0:4575|67,0:872,2596,8379|71,0:6562|72,0:420|84,0:914|89,0:4736,9343,55670|91,0:2899|92,0:251,24365|93,0:270|96,0:1016,1476,1794,2217,7505|98,0:1143,3652|99,0:1304|100,0:1470|103,0:1876,5560,9250,16125,16676,17573,17679,20298,23714,27503|104,0:518,3483|105,0:402,4087|109,0:6862|452,0:8143|460,0:11536|468,0:11167|476,0:8270"/><wd nm="mplementations" rd="89,0:10295,12321|99,0:4642|104,0:350|452,0:9813|460,0:2577|468,0:2483|476,0:9734"/><wd nm="mplemented" rd="30,0:1603|34,0:1354|56,0:13183|65,0:283|70,0:349|88,0:107|89,0:131|100,0:509|103,0:2528|104,0:1624"/><wd nm="mplementedexception" rd="17,0:8466|91,0:3336,4024"/><wd nm="mplementing" rd="89,0:2674,55840|91,0:3579|104,0:3066"/><wd nm="mplements" rd="439,0:177"/><wd nm="mplemousses" rd="275,0:359"/><wd nm="mpler" rd="18,0:3173|35,0:1676|77,0:856"/><wd nm="mples" rd="0,0:5234,5517,5953|15,0:6645|18,0:2973|33,0:80|37,0:90|41,0:192|47,0:92,129,215,321,503,546|58,0:474|60,0:77,214,576|61,0:598|63,0:525,746|64,0:337|65,0:894|66,0:335|67,0:9288|69,0:254|72,0:686|82,0:3564|86,0:1567|89,0:16227|90,0:5472,5526,6323,6416|92,0:22442|95,0:1236,2962,4379|96,0:2334|98,0:2872,3022,3398|102,0:920|104,0:2949,3145|107,0:328|434,0:85|441,0:218|447,0:822|452,0:176,765,815|453,0:694|455,0:847|460,0:192,798,848|461,0:720|463,0:849|468,0:195,800,850|469,0:724|471,0:807|476,0:169,759,806,1896|477,0:716"/><wd nm="mplest" rd="33,0:142|35,0:1726|37,0:158|41,0:182|440,0:52|453,0:2099|461,0:2858|469,0:2607|477,0:2510"/><wd nm="mplete" rd="13,0:13435|22,0:7292,10064|23,0:7251|24,0:8972,11581|31,0:2713|37,0:9637|42,0:351|45,0:3386|50,0:2550|63,0:3653,6005|64,0:1567|67,0:5897,6739,7274|71,0:11124|80,0:2805|83,0:589|89,0:11251,11642,11718,12027,12160,14329,32422,47661,51513,53979|91,0:8550|92,0:3799,10369,15497,17838,23379|93,0:2542|97,0:2943|98,0:4991|99,0:1296|102,0:1397,3340,3366,3472,3892,4035,4139|103,0:7227|107,0:10422|108,0:677,731,908,964"/><wd nm="mpleted" rd="42,0:1128|43,0:2600|46,0:910|56,0:14046|63,0:159|89,0:11582,12089,38796,53169|91,0:5340|92,0:3690,10260,21036,22882,23341|93,0:2443|102,0:3832,4476|107,0:10525|108,0:801"/><wd nm="mpletely" rd="0,0:3218|80,0:1908|84,0:1071|89,0:83019,83108,83208,83307|105,0:3376|435,0:1153"/><wd nm="mpletes" rd="13,0:13468|37,0:3924|53,0:944|63,0:2353|64,0:1022|71,0:1215|77,0:3743|80,0:1536,5266|81,0:3209|83,0:2589|89,0:32455,39327,54030|91,0:8614|92,0:20845|102,0:1224,1898|109,0:1655|435,0:2392"/><wd nm="mplex" rd="4,0:2985|14,0:1813|23,0:827|37,0:9544|67,0:810|89,0:26997|103,0:745"/><wd nm="mpliant" rd="115,0:193|118,0:194|120,0:189|140,0:185|141,0:189|144,0:199|148,0:189|150,0:214|151,0:192|152,0:194|154,0:199|155,0:199|157,0:203|158,0:224|159,0:271|164,0:177|165,0:182|169,0:198|170,0:192|171,0:182|174,0:212|181,0:299|183,0:222|185,0:197|189,0:205|195,0:239|196,0:192|198,0:196|204,0:178|206,0:193|208,0:241|209,0:217|210,0:184|211,0:189|214,0:182|219,0:191|220,0:217|225,0:199|230,0:198|235,0:179|244,0:207|247,0:201|248,0:202|249,0:192|251,0:179|253,0:197|254,0:194|255,0:193|256,0:189|259,0:203|261,0:183|262,0:202|263,0:227|264,0:242|266,0:189|268,0:177|271,0:234|274,0:207|275,0:204|277,0:198|278,0:213|285,0:199|288,0:192|290,0:192|291,0:184|295,0:206|297,0:218|301,0:203|305,0:186|306,0:191|309,0:223|322,0:192|325,0:213|326,0:181|327,0:189|328,0:242|332,0:222|334,0:228|338,0:187|343,0:189|347,0:184|349,0:249|351,0:214|354,0:192|355,0:189|356,0:226|358,0:214|362,0:224|363,0:192|366,0:224|370,0:179|373,0:200|374,0:181|375,0:212|377,0:204|380,0:187|382,0:209|383,0:197|385,0:183|386,0:200|388,0:177|389,0:186|390,0:243|391,0:196|393,0:219|394,0:186|396,0:189|409,0:209|410,0:194|414,0:194|428,0:187|430,0:189|431,0:199"/><wd nm="mplicity" rd="453,0:461|461,0:487|469,0:490|477,0:477"/><wd nm="mplify" rd="61,0:1785"/><wd nm="mployed" rd="446,0:3215,3248,5085,5476,5574,6015,6048,6240,6469,7099|447,0:571|448,0:820|449,0:1051,1145,1662|454,0:4891,4945,4975,6671,7099,7197,7588,7642,7672,7873,8102,8603|455,0:578|456,0:827|457,0:1067,1161,1681|462,0:4507,4558,4588,6394,6822,6920,7321,7372,7402,7618,7847,8277|463,0:581|464,0:830|465,0:1070,1164,1684|470,0:2623,2663,4487,4888,4973,5219,5269,5461,5692,6312|471,0:567|472,0:816|473,0:1088,1182,1712"/><wd nm="mployee" rd="12,0:979,1492"/><wd nm="mployees" rd="12,0:1309,1320"/><wd nm="mployment" rd="446,0:5042,5545,6414|447,0:201,535|448,0:1224,1506|449,0:939,1095|454,0:4738,6628,7168,7435,8047|455,0:208,542|456,0:1231,1513|457,0:955,1111|462,0:4335,6351,6891,7149,7792|463,0:211,545|464,0:1234,1516|465,0:958,1114|470,0:2509,4444,4944,5105,5636|471,0:200,531|472,0:1217,1498|473,0:967,1132"/><wd nm="mply" rd="9,0:276,1064,1843,2624,3686|10,0:2943|17,0:2224|28,0:483|61,0:1212|77,0:2623|448,0:928|452,0:6809|456,0:935|460,0:9708|464,0:938|468,0:9227|472,0:923|476,0:6995"/><wd nm="mpo" rd="165,0:321|276,0:562|313,0:435"/><wd nm="mpolė" rd="258,0:303"/><wd nm="mponent" rd="13,0:20620,23712,31772|30,0:128,141,348,996,1786,1953,2063,3754,3799,3934,4013,4062,4208,4294,4378,4426,4500,4509,4561,4699|31,0:111,1378,2955,3051,3186,3291,3359,3408,3554,3640,3724,3772,3846,3855,3907,4045|32,0:627,809,860,1098,1140,1218,1247|33,0:257,521,563,641,670,836,895,1204,2273,2316,2362,2410,2747,2840,2978,3040,3213,3357,3536,3744,3784,3852,4324,4421,4585,4731,4817,4928,4976,5050,5059,5111,5311,5387,5688,5936,6103,7033,7129,7264,7343,7392,7538,7624,7708,7756,7830,7839,7891,8029,8160,8353,8568,8699,8794,9156,9511,9573,9756,9778,9899,10015,10077,10133,10248,10379,10458,10507,10653,10739,10810,10845,10893,10959,11030,11086,11159,11212,11267,11342,11351,11403,11525,11576,11627,11681,11763,11821,11879,11947,12009,12082,12192,12416|34,0:126,154,766,1593,2271,2313,2393,2577,3033|35,0:171,233,400,607,925,953,999,1031,1292,1824,2948,3306,3348,3428,3769,4015,4269,4562,4624,4692,4837,4986,5036,5471,6320,6362,6470,6546,6638,6711,6759,6833,6842,6894,7025,7184,7227,7551,7675,7740,8029,8205|36,0:454,636,689,927,969,1047,1076|37,0:270,531,573,651,680,785,853,965,1011,1059,1396,1489,1627,1689,1862,2009,2188,2306,2465,2512,2580,2822,2972,3140,3517,3579,3635,3750,3868,4009,4231,4845,4915,4933,5242,5776,5878,6066,6229,6514,6751,6840,7110,7132,7253,7369,7431,7487,7603,7697,7732,7780,7845,7916,7972,8045,8098,8153,8228,8237,8289,8411,8462,8513,8567,8649,8707,8765,8833,8894,9004,9107,9211,9605|38,128:45,58,119,188,459,573,700,762,869,911,1005,1040,1088,1153,1224,1280,1353,1406,1461,1536,1545,1597,1719,1770,1821,1875,1957,2015,2073,2141,2202,2312,2426,2532,2641,2797|41,0:2462|42,0:532,1378,2195|43,0:529,596,721,746,833,923,1038,1080,1158,1187|45,0:44,244,587,628,664,997,1194,1236,1314,1343,1969,2398,5071,5950,6169|46,0:532,1351,1804,1943,2935,2991,3032,3460,3534,3577,3602,3677,3773,3907,4004,4098,4225,4320,4475,4530,4657,4755,4834,4972,5069,5111,5189,5218,5300,5582,5670,5708,5870,6062,6094,6258,6389,6479,6847,6883,6933,7125,7380,7611,7628,7658,7781,8405|47,0:1560,2033,2186,2263,2520,2588,2630,2708,2737,2816,3443|48,0:1175|49,128:47,68,92,225,753,823,864,1653,6166|50,0:798,839,1176|51,0:171,1220,1280,1436,2549,2657,2722,3054,3087,4807,4867,5023,6286,6394,6457,6611,6928,7548,7611,7763,7959|57,0:2905|62,0:1772,2135,2208,4466|82,0:1243,1309,1365|86,0:2031,3692,3896|89,0:1974,2016,2094,2123,56937,56955,57005|90,0:3715,3757|434,0:4949|436,0:2904|458,0:12287|466,0:11575"/><wd nm="mponent2" rd="35,0:3811,3892"/><wd nm="mponent_instance" rd="37,0:9148|38,0:2467"/><wd nm="mponentattributes" rd="30,0:4079,4225,4311,4395,4443,4526,4578|31,0:3425,3571,3657,3741,3789,3872,3924|33,0:4602,4748,4834,4945,4993,5076,5128,7409,7555,7641,7725,7773,7856,7908,8585,8811,9173,9528,9590,10524,10670,10756,10862,10910,10976,11047,11103,11176,11229,11284,11368,11420,11542,11593,11644,11698,11780,11838,11896,11964,12026,12099|35,0:6487,6563,6655,6728,6776,6859,6911,8046|37,0:7749,7797,7862,7933,7989,8062,8115,8170,8254,8306,8428,8479,8530,8584,8666,8724,8782,8850,8911,9166,9228|38,0:1057,1105,1170,1241,1297,1370,1423,1478,1562,1614,1736,1787,1838,1892,1974,2032,2090,2158,2219,2485,2549|49,0:304,506,535,588|51,0:452,1146,4743,5223"/><wd nm="mponents" rd="35,0:4281|42,0:1266|45,0:1406|63,0:3938|64,0:2449|89,0:53623,53761|91,0:7397,7803|460,0:11169|468,0:10802"/><wd nm="mpong" rd="154,0:333,353,376,395"/><wd nm="mpopo" rd="364,0:341"/><wd nm="mporary" rd="44,0:4013|56,0:1200,3462"/><wd nm="mporia" rd="415,0:2055"/><wd nm="mportant" rd="12,0:325|33,0:2639|37,0:1288|38,0:617|41,0:229|44,0:4830,5061|56,0:4275,4506,5367,6172,9266|63,0:10503|64,0:3972,4747|68,0:6262|72,0:2843|78,0:1511|79,0:4150|81,0:514|82,0:4115|88,0:720|89,0:871,2193|90,0:6215,6288|433,0:3181|435,0:1645,4089|436,0:6055|437,0:235|450,0:104|458,0:111|466,0:114|474,0:104"/><wd nm="mportantly" rd="8,0:510|15,0:7231|68,0:3887"/><wd nm="mports" rd="462,0:1081,2375,2448|466,0:978,1939,2012,11687,11715,11737,11755,11772,13576|467,0:1334|468,0:3737|469,0:1533"/><wd nm="mposite" rd="111,0:1131"/><wd nm="mposition" rd="21,0:1284"/><wd nm="mpostela" rd="332,0:710"/><wd nm="mpot" rd="154,0:415"/><wd nm="mprehend" rd="15,0:1281"/><wd nm="mprehensive" rd="65,0:7201"/><wd nm="mprehensively" rd="23,0:234,997|67,0:232,1153|103,0:234,916"/><wd nm="mpressed" rd="44,0:3964|46,0:2497,6359|56,0:3413|62,0:1156"/><wd nm="mprin" rd="257,0:309"/><wd nm="mprint" rd="439,0:1345|442,0:674|444,0:819"/><wd nm="mprinted" rd="439,0:1416|442,0:721|444,0:866"/><wd nm="mprised" rd="81,0:94"/><wd nm="mprises" rd="44,0:3278|80,0:1253|81,0:477"/><wd nm="mproper" rd="60,0:2035|65,0:5149"/><wd nm="mproved" rd="90,0:329,2326,4589,4740,5535"/><wd nm="mps" rd="88,0:781"/><wd nm="mpshire" rd="85,0:2309,2319,2341,37187,41299|89,0:73743,77855,86836,86846|193,0:519|273,0:414|299,128:3,36,78,99,137,564|401,0:780|403,0:457|420,0:469"/><wd nm="mpshireareacode" rd="85,0:37208,37238|89,0:73764,73794"/></pk>