<?xml version="1.0" encoding="UTF-8" standalone="no"?>
<pk><wd nm="g1" rd="303,0:483|396,0:420"/><wd nm="g2" rd="303,0:498|396,0:1661"/><wd nm="g2all" rd="44,0:3483,4123|56,0:3081,3572"/><wd nm="g3" rd="303,0:516|396,0:1255"/><wd nm="g4" rd="396,0:890"/><wd nm="g5" rd="396,0:451"/><wd nm="g6" rd="396,0:1719"/><wd nm="g7" rd="396,0:941"/><wd nm="g8" rd="396,0:1336"/><wd nm="g9" rd="396,0:973"/><wd nm="g_language" rd="46,0:2446"/><wd nm="ga" rd="85,0:11115,11121,11136,18466,18472,18487,24774,24782,24810,31131,31136,31150,31602,31608,31623|89,0:67889,67894,67908,68360,68366,68381,96434,96440,104286,104292,105426,105434|113,0:623|114,0:256,1312|124,0:622|132,0:535|140,0:373|141,0:328,335,338|150,0:348,557,608,691,758,838,954|152,0:395,490|159,0:662|169,0:628|181,0:487|187,0:545|190,0:362|198,0:369,372|204,0:407|206,0:621|208,0:853,856|210,0:268,285,305,326,342,350,357,379,399,423|212,0:715|219,0:459,462|220,0:376,379|222,0:272|230,0:704|237,0:372|241,0:769,800|245,0:816|252,0:478,625,637|257,0:306|262,0:1445|263,0:380|264,0:385|266,0:437,584|268,0:277,280|272,0:490|276,0:680|277,0:396,769|282,0:809|283,0:301,361|285,0:426,429|286,0:525|289,0:283|292,0:713|293,0:287,290|302,0:347,855,1054,1227|304,0:308,368|309,0:839,1721|319,0:477|320,0:549,707,728|321,0:584|328,0:430|330,0:1170|332,0:938,1347,1710,1736,1760|334,0:3328|335,0:282|337,0:1352,1368|339,0:413|342,0:637|347,0:288,323,344,363,419|354,0:359|363,0:348,351|364,0:355|371,0:498|372,0:620,784|383,0:338,588,637|386,0:974|389,128:0,26,61,78,109,430|392,0:718|394,0:294|396,0:399,413,761|401,0:436,440|406,0:345|408,0:375|415,0:2169|417,0:477|426,0:1207,3217|437,0:1093,3883"/><wd nm="gaal" rd="363,0:457"/><wd nm="gab" rd="256,0:440"/><wd nm="gabes" rd="391,0:348"/><wd nm="gabon" rd="85,0:11981,11987,12002|89,0:97389,97395|113,0:627|210,0:0,26,78,109|426,0:1210"/><wd nm="gabonmap" rd="210,0:61"/><wd nm="gabrovo" rd="85,0:19138,19146,19163|89,0:59750,59758,59775|149,0:301"/><wd nm="gabu" rd="220,0:382"/><wd nm="gabytes" rd="6,0:4364"/><wd nm="gac" rd="460,0:1683,1737,1877,2357|468,0:1589,1643,1783,2263"/><wd nm="gacy" rd="17,0:8208|59,0:414|89,0:40956|92,0:6025|97,0:2376,2414|99,0:1021,3045,5296"/><wd nm="gadahoc" rd="265,0:458"/><wd nm="gadan" rd="342,0:936"/><wd nm="gadez" rd="305,0:277"/><wd nm="gadi" rd="144,0:320"/><wd nm="gadid" rd="85,0:33738,33744,33763|89,0:70426,70432,70451"/><wd nm="gado" rd="289,0:272"/><wd nm="gadsden" rd="206,0:625"/><wd nm="gae" rd="85,0:29682,29690,29712,29838,29846,29868|89,0:66440,66448,66470,66596,66604,66626"/><wd nm="gaemauga" rd="347,0:344"/><wd nm="gafjar" rd="228,0:593"/><wd nm="gafsa" rd="391,0:362"/><wd nm="gagaemauga" rd="347,0:344"/><wd nm="gagaifomauga" rd="347,0:363"/><wd nm="gage" rd="292,0:716"/><wd nm="gago" rd="396,0:1084"/><wd nm="gai" rd="285,0:290,548|385,0:1541|414,0:1067"/><wd nm="gaifomauga" rd="347,0:363"/><wd nm="gaillimh" rd="237,0:376"/><wd nm="gain" rd="1,0:2052|4,0:5038|5,0:1545|6,0:3323,4373|7,0:2120|11,0:1472|16,0:1619|18,0:1864|19,0:309|20,0:592|21,0:1223|23,0:8033|25,0:2973|26,0:780|35,0:572|43,0:2681|45,0:2668,5050,5354|46,0:6703|47,0:475|63,0:7534,12840|64,0:5815|66,0:277|67,0:6286,7657|77,0:3551|81,0:5704|89,0:17847,24585,29046,43876,44579,45306,54718|91,0:1753|92,0:10802,11301,12069|103,0:8009|450,0:5645|458,0:8653|466,0:8073|474,0:5873"/><wd nm="gaines" rd="385,0:1545"/><wd nm="gaing" rd="151,0:492"/><wd nm="gainst" rd="438,0:2988|447,0:392|450,0:5485,6392|455,0:399|458,0:8488,10373|463,0:402|466,0:7907,9765|471,0:388|474,0:5735,6663"/><wd nm="gal" rd="85,0:5185,5194,5212,12770,12778,12795,18392,28235,28242,28262|89,0:84292,89894,89903,98290,98298,104196,109108,109115|90,0:4527|113,0:979|190,0:365|199,0:744|200,0:820|202,0:809|231,0:970|335,128:0,29,67,87,121,605|354,128:0,28,65,84,117,552|368,0:450|385,0:1556|426,0:1486,2807"/><wd nm="gala" rd="373,0:509,573|396,0:355"/><wd nm="galagadi" rd="144,0:320"/><wd nm="galand" rd="85,0:23623,23632,23650,27859,27868,27886|89,0:64235,64244,64262,84108,108686,108695|231,0:771|315,0:434|316,0:472"/><wd nm="galapagos" rd="89,0:82565|365,0:547"/><wd nm="galax" rd="415,0:2172"/><wd nm="galaţi" rd="341,0:489"/><wd nm="galbeed" rd="363,0:574"/><wd nm="galguduud" rd="363,0:354"/><wd nm="gali" rd="343,0:296"/><wd nm="galia" rd="420,0:719"/><wd nm="galicia" rd="371,0:501"/><wd nm="gall" rd="237,0:334"/><wd nm="gallanes" rd="165,0:441"/><wd nm="gallatin" rd="230,0:707|245,0:819|286,0:529"/><wd nm="galle" rd="373,0:378,473"/><wd nm="gallen" rd="85,0:17769,17776,17797|89,0:103509,103516|379,0:498"/><wd nm="gallery" rd="31,0:2068|50,0:1751|82,0:3837,3939,4052|90,0:6399"/><wd nm="gallia" rd="320,0:711"/><wd nm="galloway" rd="352,0:484|353,0:325"/><wd nm="galo" rd="349,0:359"/><wd nm="galore" rd="89,0:84013"/><wd nm="galpa" rd="304,0:434"/><wd nm="galpha" rd="0,0:887,1505|1,0:4186|11,0:498,1123,1230,1455,1527,1777,2148|13,0:6652,14803,16432|14,0:951|71,0:4799,5676|89,0:33573,41827|92,0:6905,13503,13682,15776|95,0:2054,2445,2903,2929|106,0:3344,4217,11104,11977|107,0:2274,3149,8406|109,0:4891,5764|110,0:3667,4540|452,0:8533"/><wd nm="galveston" rd="385,0:1560"/><wd nm="gamaa" rd="85,0:21665,21674,21692|89,0:62277,62286,62304|197,0:440"/><wd nm="gambela" rd="198,0:375"/><wd nm="gambia" rd="85,0:12008,12015,12031|89,0:97424,97431|113,0:1242|211,0:0,27,63,81,113|426,0:1696"/><wd nm="gamie" rd="421,0:939"/><wd nm="gamo" rd="396,0:1753"/><wd nm="gamon" rd="230,0:1495"/><wd nm="gampaha" rd="373,0:392"/><wd nm="gamprin" rd="257,0:309"/><wd nm="gan" rd="85,0:2051,2060,2078,29514,29522,29544,29595,29603,29625,36764,40771|89,0:66272,66280,66302,66353,66361,66383,73320,77327,86544,86553|112,0:621,695|114,0:1157|124,0:873|147,0:423,676,713|169,0:858,945|212,0:2058|230,0:1061,1281|232,0:1047|235,0:448|243,0:1197|245,0:1283,1533|277,128:0,29,67,87,121,327,549,1703|282,0:1313|285,0:348|292,0:1047|310,0:609|313,0:448,470|320,0:1024,1195|321,0:848|335,0:294|342,0:873|384,0:1210|385,0:3234|401,0:650|402,0:334|403,0:439|408,0:477|409,0:362|416,0:600|417,0:677|420,0:605,751|421,0:1148"/><wd nm="ganareacode" rd="85,0:36781,36807|89,0:73337,73363"/><wd nm="ganca" rd="85,0:18493,18502,18520|89,0:104321,104330"/><wd nm="gancongressional" rd="85,0:40793,40824|89,0:77349,77380"/><wd nm="ganda" rd="85,0:13232,13239,13255|89,0:83256,98698,98723|113,0:1165|396,128:0,27,63,81,113,1909|426,0:1635"/><wd nm="gandaki" rd="293,0:293"/><wd nm="gandi" rd="327,0:398,423"/><wd nm="ganem" rd="118,0:733"/><wd nm="gang" rd="85,0:29386,29396,29415,29425,29433,29450|89,0:66144,66154,66173,66183,66191,66208|141,0:503,520|313,0:283,510"/><wd nm="ganga" rd="396,0:761"/><wd nm="gangle" rd="11,0:727,1155,1262|13,0:6827"/><wd nm="gangsan" rd="85,0:29758,29769,29789|89,0:66516,66527,66547"/><wd nm="gangwon" rd="369,0:368"/><wd nm="gangwondo" rd="85,0:28789,28799,28818|89,0:65547,65557,65576"/><wd nm="gani" rd="332,0:1458"/><wd nm="ganizes" rd="83,0:406,926"/><wd nm="gannon" rd="312,0:502"/><wd nm="gano" rd="85,0:31737,31744,31760|89,0:68495,68502,68518|241,0:641|347,0:456"/><wd nm="ganski" rd="334,0:1624"/><wd nm="gansu" rd="85,0:29957,29963,29978|89,0:66715,66721,66736|166,0:288|167,0:542"/><wd nm="gant" rd="43,0:1266|274,0:480"/><wd nm="ganu" rd="267,0:477"/><wd nm="ganui" rd="85,0:34628,34637,34663|89,0:71250,71259,71285|303,0:363"/><wd nm="gany" rd="272,0:279|302,0:273"/><wd nm="ganzourgou" rd="150,0:413"/><wd nm="gao" rd="268,0:283|332,0:854,1614,1638"/><wd nm="gaos" rd="85,0:25025,25033,25050|89,0:105697,105705"/><wd nm="gaoual" rd="219,0:465"/><wd nm="gap" rd="13,0:19823,19843,19954,34333,34413|89,0:30629,30659,56293,56322|432,0:4734,4814"/><wd nm="gapore" rd="85,0:9713,9723,9742|89,0:94799,94809|126,0:749|127,0:677|359,128:0,30,69,90,125,272,294,317,340,362,472|426,0:2149"/><wd nm="gar" rd="85,0:27171|89,0:82104,107941|112,0:560|141,0:401|230,0:605|231,0:428|385,0:1574"/><wd nm="gara" rd="89,0:84044|233,0:443,774|302,0:820|323,0:667"/><wd nm="garaard" rd="326,0:384"/><wd nm="garchelong" rd="326,0:401"/><wd nm="gard" rd="208,0:859|259,0:375"/><wd nm="garden" rd="292,0:728"/><wd nm="garding" rd="17,0:1065|42,0:2048|449,0:930|457,0:946|465,0:949|473,0:958"/><wd nm="gardmau" rd="326,0:421"/><wd nm="gardzki" rd="334,0:360,572,723"/><wd nm="gareacode" rd="85,0:38907,38932|89,0:75463,75488"/><wd nm="garfield" rd="169,0:631|286,0:548|292,0:742|321,0:587|408,0:379|417,0:462"/><wd nm="garfjar" rd="228,0:370"/><wd nm="garh" rd="85,0:27076,27087,27107,27118,27130,27151|89,0:82072,83966,107841,107852,107886,107898|231,0:376,397"/><wd nm="garhar" rd="112,0:574"/><wd nm="garhaveli" rd="85,0:27183,27212|89,0:107953"/><wd nm="gari" rd="387,0:318"/><wd nm="garia" rd="85,0:3868,3877,3895,19010|89,0:59622,88486,88495|149,128:0,29,67,87,121,747|188,0:322|199,0:352|200,0:388|202,0:417|426,0:2415"/><wd nm="garland" rd="124,0:625"/><wd nm="garman" rd="237,0:721"/><wd nm="garmatha" rd="293,0:433"/><wd nm="garonne" rd="208,0:945,1325,1836"/><wd nm="garrard" rd="245,0:835"/><wd nm="garrett" rd="272,0:494"/><wd nm="garvin" rd="321,0:603"/><wd nm="garwolinski" rd="334,0:3331"/><wd nm="gary" rd="85,0:4401,4409,4426,4434,20238,20263,20271,20295,20453,20461,20486|89,0:60850,60875,60883,60907,61065,61073,61098,89084,89092,89123|117,0:326|163,0:371|199,0:492|200,0:537|202,0:557|226,128:0,28,65,84,117,677|227,128:0,35,297,376,568|323,0:923|426,0:2555"/><wd nm="garyregions" rd="85,0:4451,4475|89,0:89140|227,0:79,105,145"/><wd nm="garza" rd="385,0:1578"/><wd nm="gas" rd="85,0:19075,19082,19098|89,0:59687,59694,59710|149,0:274|332,0:475|400,0:253|412,0:489,574"/><wd nm="gasa" rd="141,0:341"/><wd nm="gasaki" rd="85,0:31095,31104,31122|89,0:67853,67862,67880|241,0:657"/><wd nm="gascar" rd="85,0:12264,12275,12295,12306|89,0:97731,97742,97776|113,0:768|263,128:0,40,89,111,147,524|264,128:0,38,879|426,0:1319"/><wd nm="gascarregions" rd="85,0:12326,12353|89,0:97796|264,0:85,114,157"/><wd nm="gasconade" rd="282,0:812"/><wd nm="gash" rd="196,0:338"/><wd nm="gasinan" rd="332,0:1364"/><wd nm="gasp" rd="339,0:416"/><wd nm="gasta" rd="165,0:333"/><wd nm="gastani" rd="262,0:956"/><wd nm="gaston" rd="309,0:842"/><wd nm="gat" rd="392,0:1355"/><wd nm="gata" rd="85,0:31863,31871,31888,32151,32160,32178|89,0:68621,68629,68646,68909,68918,68936|241,0:689,952"/><wd nm="gatapu" rd="389,0:306"/><wd nm="gated" rd="15,0:4279,4544"/></pk>