<?xml version="1.0" encoding="UTF-8" standalone="no"?>
<pk><wd nm="bilgorajski" rd="334,0:3597"/><wd nm="bili" rd="391,0:428"/><wd nm="biliran" rd="332,0:508"/><wd nm="bilisi" rd="128,0:497"/><wd nm="bilities" rd="21,0:1772|23,0:6757,6802|27,0:259|42,0:2632|46,0:1598|84,128:17,237,1023,2094|86,0:2335|89,0:9908|103,0:6733,6778|104,0:1327"/><wd nm="bility" rd="15,0:6368|16,0:3013|17,0:5116|33,0:3909|34,0:1209|35,0:4125|37,0:2636|42,0:2057|43,0:968|44,0:2391,2750|63,0:9390,13648|64,0:6623|65,0:2877,2900|84,0:463|89,0:41579|90,0:247,573,1993,4066,4244,4910,4978,5099|91,0:2124|92,0:6657|96,0:8487|100,0:4632|106,0:3035,10795|107,0:1966|109,0:4583|110,0:3358|452,0:7648|460,0:10548|468,0:10067|476,0:7835"/><wd nm="billings" rd="310,0:314"/><wd nm="billion" rd="6,0:1031|10,0:496,610,908,1004"/><wd nm="billions" rd="6,0:868,984,1834,1907"/><wd nm="bilogorska" rd="175,0:264"/><wd nm="biləsuvar" rd="132,0:436"/><wd nm="bim" rd="396,0:1058"/><wd nm="bimini" rd="133,0:286"/><wd nm="bin" rd="454,0:1699|458,0:1574|459,0:2012|460,0:1345,1373,1809,6246,9327|461,0:4257|462,0:1509|466,0:1381|467,0:1373,1807|468,0:1251,1279,1715,3775,5874,8845|469,0:1572,3961"/><wd nm="bina" rd="270,0:359|310,0:756"/><wd nm="binarywrite" rd="8,0:2766,2934,3200,3231,3262"/><wd nm="bination" rd="33,0:4241|89,0:21043,21697,21820|104,0:2778|438,0:1285|444,0:2401|467,0:3333"/><wd nm="binations" rd="0,0:4736|4,0:3467|89,0:21275,22281,27475"/><wd nm="binci" rd="262,0:805"/><wd nm="bind" rd="71,0:11085|107,0:9496,10417|108,0:245,278,671,726,890|109,0:9675"/><wd nm="binda" rd="120,0:323"/><wd nm="binds" rd="104,0:277|109,0:9688"/><wd nm="bine" rd="21,0:1155|69,0:148|98,0:3171|259,0:996|385,0:3390"/><wd nm="bined" rd="14,0:526|43,0:1248"/><wd nm="bing" rd="182,0:441|392,0:503"/><wd nm="bingham" rd="229,0:331"/><wd nm="bingo" rd="76,0:3579|438,0:3083"/><wd nm="binh" rd="414,0:402,419,437,455,774,966,1032,1166"/><wd nm="bini" rd="293,0:355"/><wd nm="bining" rd="56,0:11856"/><wd nm="binje" rd="89,0:81709|143,0:652"/><wd nm="binsk" rd="342,0:419"/><wd nm="binski" rd="334,0:3988"/><wd nm="bioko" rd="195,0:345,364"/><wd nm="biombo" rd="220,0:322"/><wd nm="bion" rd="384,0:1224"/><wd nm="bique" rd="85,0:12539,12550,12570|89,0:98034,98045|113,0:860|289,128:0,31,71,93,129,517|426,0:1391"/><wd nm="bir" rd="249,0:380"/><wd nm="birabad" rd="132,0:889"/><wd nm="birizi" rd="396,0:1768"/><wd nm="birsk" rd="342,0:1111"/><wd nm="bishkek" rd="250,0:315"/><wd nm="biskra" rd="118,0:411"/><wd nm="bismarck" rd="437,0:2618"/><wd nm="bispo" rd="153,0:983"/><wd nm="bissau" rd="85,0:12102,12109,12131|89,0:97540,97547|113,0:683|220,0:6,39,75,99,137,337|426,0:1254"/><wd nm="bistip" rd="262,0:1277"/><wd nm="bistriţa" rd="341,0:310"/><wd nm="bit" rd="23,0:13979,14516|47,0:3558|57,0:676,707,742,805,830|72,0:2417|103,0:14316|105,0:4217"/><wd nm="bitary" rd="293,0:516"/><wd nm="bitibi" rd="339,0:260"/><wd nm="bitlis" rd="392,0:516"/><wd nm="bitmap" rd="43,0:475,615,2069|46,0:586,700,1169,2507,3267,3349,4869,6369,7432|53,0:502|55,0:520,1033|62,0:700,1166"/><wd nm="bitoke" rd="152,0:378"/><wd nm="bitola" rd="262,0:343"/><wd nm="bits" rd="6,0:4354,4398,4434,4558,4665"/><wd nm="biu" rd="341,0:677"/><wd nm="biya" rd="85,0:33150,33159,33177,33499,33510,33530|89,0:69838,69847,69865,70187,70198,70218|256,0:280"/><wd nm="bizerte" rd="391,0:332"/><wd nm="bizi" rd="159,0:532"/><wd nm="bizkaia" rd="372,0:426"/><wd nm="bj" rd="28,0:453,516|89,0:81615|92,0:13978,14209|98,0:645,762,966,1075|113,0:283|118,0:390,393|140,0:267,283,299,318,333,350,365,379,396,409,423,439|143,0:582|167,0:487,490|211,0:273,276|391,0:296,299|396,0:729|426,0:931"/><wd nm="bjconfiguration" rd="92,0:15804"/><wd nm="bject" rd="1,0:2558|10,0:1872|12,0:98,874,1236,1349,1462,2818,2953,3247,3337|13,0:1885,2594,3107,6138,6218,6351,6489|17,0:1265,1785,1797,3005,3038,4865,8101,8113,8164,8250,8262,8313|22,0:6974,7537,7636,7692,8336,8386,8488,8532,8552,8591,8684,8862,9729|28,0:444|30,0:514,742,3820|31,0:130,3072,4129|33,0:3557,3660,7150,10269|34,0:635,2334|35,0:3369,3833,6383|37,0:2209,2381,3771,7624|38,0:932|41,0:1070,2874,2909,2932,3248,3283,3306,4024,4327,4359|43,0:842|45,0:405,469,539,602,742,830,909,1067,1438,1654,1717,1733,1801,2551,2811,3405,3515,3552,3768,3824,3918,4122,4162,4366,4451,4647,4933,5237,5668|47,0:2340|49,0:333,410,704,838|50,0:158,204,337,414,682,813|51,0:57,63,107,197,375,394,446,472,577,854,1093,1166,1488,1610,1940,2283,2764,2789,2823,2860,2916,3567,3639,3652,3716,3789,3849,3934,4054,4154,4342,4386,4635,4688,4763,5075,5180,5260,5580,5684,5974,6159,6474,6659,6777,7663,7686|56,0:12583|57,0:356|61,0:1969|63,0:4172,8976,9065,11591|65,0:18,54,208,248,470,652,1213,1829,1972,2147,2622,2664,2781,2946,3065,3113,3219,3469,4623,5712,6597|66,0:126,1414,2686,2816|67,0:8017|69,0:1742,2373|71,0:3267,3417,3451,4177,4404,6543,8143,8324|72,0:5864|74,0:855|79,0:5750|81,0:407|89,0:7112,9319,10126,10615,13380,13616,14654,14952,16088,35691,36032,36406,36817,36938,37153,38168,38349,38447,38904,38916,40993,41020,42468,42576,42697,42912,43152,43290,43352,44979,45957,46241,46821,46852,47093,47206,47600,48062,48177,48413,48553,49266,50369,50442,50462,50612,50877,51058,51772,52141|91,0:555,618,673,917,964,1138,1202,1221,1418,1845,1861,1913,1933,2387,2403,2455,2491,2729,2745,2797,2833,3099,3115,3167,3187,3453,3787,3803,3855,3875,4141,4403,4419,4471,4491,5024,5040,5092,5112,5290,5314,5466,5482,5534,5554,5763,5787,6011,6027,6079,6099,6275,6299,6499,6515,6567,6587,6756,7026,7042,7094,7114,7576,7592,7645,7681,7972,7988,8040,8076,8439,8455,8507,8543,8789,8805,8857,8877,9398,9414,9466,9486,10057,10557,10573,10625,10645,11267,11657,11673,11725,11745,12376,12392,12444,12480,12614,12630,12682,12702,12902,12918,12970,12990,13086,13257,13273,13325,13345,13442,13607,13623,13675,13695,13965,14137,14153,14409,14425,14477,14497,15003,15019,15071,15091,15607,15623,15675,15695,15975,15991,16043,16063,16943,16959,17011,17031,17906,17922,17974,17994,18880,18896,18948,18968,19249,19265,19317,19337,19613,19629,19681,19701,20162,20178,20230,20250,20311,20639,20674,21013,21029,21081,21117|92,0:455,670,759,781,986,1083,1320,1345,1365,1416,1547,2002,2097,2151,2305,2651,2774,2989,3135,3272,3484,3525,4013,6062,6089,7551,7659,7780,7995,8249,8387,8449,8508,8948,9203,9234,9953,10066,11381,11474,12545,12829,13919,14197,15069,15437,15821,16249,16367,16603,16739,17941,18010,18327,18396,18714,18777,18850,18870,19018,19962,20024,20074,20086,20598,22616,22832,23005,23030,23461,23632,23657,23947,24144,24489,24583,24619,24639|93,0:980,1011,1256|94,0:536,740,828,884,978,1004,1107,1415,2035,2099,2141,2225,2391,2472,2555,2670,3004,3120,3449,3541|95,0:1108,1135,2323,2392,2525,2695,3105,3711,3776,4334,4508,4548|96,0:1921,1981,3833,5103,5171,7351,8341,8378,8419|97,0:577,688,715,770,851,932,979,1000,1047,1145,1807,1907,2099,2208,2300,2329,2536,2560,2634,2679,2853|98,0:616,1848,2163,2237,2262,2575,2690,2768,2862,3086,3279,3463,4138,4212,4234,4644,4684,4948|99,0:863,1001,1068,1099,1200,1869,2020,2159,2475,2613,3094,3124,4421,4683,5348,5378,6567|100,0:2512,2545,4381|101,0:1294,1898,1910,1988,2030,2359,3507,3878,3890,3918,3944,3969,3990,4017,4050,4082,4113,4374,5952,5964,6027,6055,6300,7810,7822,7890,7918,8176,8695,8707,8744,8785,9061,9653,9665,9748,9793,10064,10643,10655,10745,10790,11052,11955,11967,12023,12055,12309,13207,13219,13280,13312,13617,13942|102,0:2663,3244,3258,3774,3786,3809,4275,4323,4366,4418,4430,4453,5014,5061,5240,5305,5325|103,0:13813,22721|104,0:494,1548|105,0:1037,1327,2646,3530,3550|106,0:2675,2902,5147,5328,6928,9652,10435,10662,12814,12893|107,0:398,749,1606,1833,3981,4331,4638,4993,5317,5794,6170,7025,8002,8091,10457,10469,10502|108,0:358|109,0:3296,3451,3485,4223,4450,6843,7871,8052|110,0:1686,2998,3225,8059,9978,10521|434,0:2970,3011,3066|438,0:424,786,833,919,1224,1350,1602,2316,2907,3206,3301,3443,3669,4591,6818|439,0:1765,1878|440,0:107|441,0:3381|442,0:85,1984|443,0:535,597,1477,3819,3881,4014,4264,4274,4376,4439,4571,4618,4663,4724,4805|445,0:656,1363,2590,2730,2958|446,0:2203,2604,4027,4068|450,0:1979,2233,2457,3244,3286|454,0:1410,5872,5913|458,0:1320,2667,4122,5874,5915,6322,7013,8919,12657,13665,13742,13813,13977,14571,14710|459,0:1745,2813|460,0:4230|461,0:1972,2162,4044|462,0:1193,5465,5506|466,0:1101,2216,3687,5361,5402,6438,8388,12501,12858,12946,13015,13548,13691|467,0:1530,2638|468,0:3932,6523,6946|469,0:1813,2003,3753,4590|470,0:3433,3474|474,0:3357,3398"/><wd nm="bject&apos;s" rd="97,0:1211"/><wd nm="bject&gt;/&lt;embed&gt;" rd="65,128:7652"/><wd nm="bjectreference" rd="92,0:1250,1692,23241,23772|93,0:1369|96,0:8112|97,0:2729,2755,2916|99,0:4734"/><wd nm="bjects" rd="12,0:949,2143,3011|13,0:84,1539,1583,1767,1796|18,0:307|22,0:7794|33,0:2587|37,0:1236|45,0:4885|51,0:809,1025,4567|57,0:264|59,0:718|62,0:729,780|71,0:5133|73,0:793,926|81,0:77,443,497|91,0:819,1318|93,0:1180|101,0:935|102,0:323,3236,4915,5383|104,0:554|106,0:3674,11434|107,0:2606,5386,5507,9672|109,0:5221,9622|110,0:2037,3997,5900,6569,7489,8710,9500,10462|438,0:186,402,608,1132,3373|439,0:73|441,0:1667|443,0:1117,1418,3649,3728,3793,4526|444,0:90|445,0:114,326,350,415,599,628,2149,2831,2885"/><wd nm="bjelovarsko" rd="175,0:252"/><wd nm="bjjson" rd="96,0:2061,2116,2280,5131,5254,7329,7340,7843"/><wd nm="bjparams" rd="101,0:13930,14436,14540,14565,14582,14609"/><wd nm="bjrtn" rd="30,0:520,748,907,933,941,2328,2339,2403,2469,2500,2643,2654,2728,2765,2831|34,0:340,676,704,1766,1777,1841,1907,1938|56,0:12624,12652,13460,13471,13557,13642"/><wd nm="bk" rd="89,0:82659,82662|150,0:388,391|159,0:396,399|212,0:305|219,0:303,306|226,0:249|235,0:488,491|245,0:403|251,0:279,282|309,0:478|332,0:532,535|342,0:324,327|363,0:291,294|366,0:424|382,0:294,297|386,0:323,326|392,0:430|396,0:960|414,0:312,315|420,0:334"/><wd nm="bkhazia" rd="128,0:279"/><wd nm="bkit" rd="89,0:14112|105,0:191"/><wd nm="bkowicki" rd="334,0:4151"/><wd nm="bl" rd="13,0:8198,8281|89,0:81557|114,0:321|118,0:420,423|132,0:392|143,0:542|150,0:372,375|212,0:440|220,0:346,349|229,0:345|232,0:309|245,0:390|251,0:293,296|252,0:283|266,0:525,528|272,0:340|275,0:289,292|280,0:301|286,0:291|292,0:312,407|309,0:431|312,0:327|314,0:338,341|321,0:326|330,0:364|334,0:1313,5226|342,0:346,349|360,0:274|372,0:390|379,0:301|384,0:305|392,0:526|396,0:1448|414,0:327,330|415,0:431|446,0:2908,3001,5707,5800"/></pk>