<map animation='0' showShadow='0' showBevel='0' showMarkerLabels='1' fillColor='F1f1f1' borderColor='999999' baseFont='Verdana' baseFontSize='10' markerBorderColor='000000' markerBgColor='FF5904' markerRadius='6' legendPosition='bottom' useHoverColor='1' showMarkerToolTip='1' showLabels='0' >
	<data>
		<entity id='CA.PE.AL'  />
		<entity id='CA.PE.CS'  />
		<entity id='CA.PE.NC'  />
		<entity id='CA.PE.PC'  />
	</data>
	<markers>
	<shapes>
	       <shape id='myCustomShape' type='circle' fillColor='FFFFFF,333333' fillPattern='radial' showBorder='0' radius='4'/>
		   <shape id='newCustomShape' type='circle' fillColor='FFFFFF,000099' fillPattern='radial' showBorder='0' radius='3'/>
	   </shapes>
		<definition>
			<marker id='CH' x='239.4' y='221.89' label='Charlottetown'  />
			<marker id='01' x='249.86' y='227.12' label='Stratford' labelPos='right'  />
			<marker id='02' x='218.5' y='223.98' label='Cornwall' labelPos='left'  />
			<marker id='03' x='194.45' y='235.48' label='Bonshaw' labelPos='bottom'  />
			<marker id='04' x='171.45' y='229.21' label='Victoria' labelPos='left'  />
			<marker id='06' x='168.31' y='211.44' label='Crapaud'  />
			<marker id='07' x='139.04' y='216.67' label='Borden' labelPos='left'  />
			<marker id='08' x='132.77' y='197.85' label='Central Bedeque' labelPos='left'  />
			<marker id='09' x='151.59' y='183.21' label='Freetown' labelPos='left'  />
			<marker id='10' x='143.22' y='162.3' label='Kensington' labelPos='left'  />
			<marker id='11' x='195.5' y='157.07' label='Cavendish' labelPos='right' />
			<marker id='12' x='204.9' y='165.44' label='North Russo' labelPos='right'  />
			<marker id='13' x='262.4' y='192.62' label='Oyster Bed Bridge' labelPos='left'  />
			<marker id='14' x='341.86' y='177.98' label='Peters Bay'  />
			<marker id='16' x='287.5' y='186.35' label='Mount Stewart' labelPos='right'  />
			<marker id='15' x='308.4' y='174.85' label='Morell' labelPos='left'  />
			<marker id='17' x='421.31' y='170.67' label='Elmira' labelPos='left'  />
			<marker id='18' x='401.45' y='177.98' label='Baltic' labelPos='right'  />
			<marker id='19' x='372.18' y='209.35' label='Little Pond' labelPos='right'  />
			<marker id='20' x='332.45' y='278.35' label='Murray River'  />
			<marker id='21' x='347.09' y='286.71' label='Murray Harbour' labelPos='right'  />
			<marker id='22' x='312.59' y='294.03' label='Wood Islands' labelPos='left'  />
			<marker id='23' x='289.59' y='278.35' label='Belle River' labelPos='left'  />
			<marker id='24' x='284.36' y='235.48' label='Vernon Bridge' labelPos='bottom'  />
			<marker id='25' x='309.45' y='217.71' label='Vernon River'  />
			<marker id='26' x='330.36' y='225.03' label='Cardigan' labelPos='right'  />
			<marker id='27' x='136.95' y='145.57' label='Malpeque' labelPos='right'  />
			<marker id='28' x='93.04' y='134.07' label='Tyne Valley' labelPos='right'  />
			<marker id='29' x='86.77' y='120.48' label='Ellerslie' labelPos='right'  />
			<marker id='30' x='64.81' y='112.12' label='West Devon' labelPos='right'  />
			<marker id='31' x='28.22' y='101.67' label='Knutsford' labelPos='right'  />
			<marker id='32' x='44.95' y='87.03' label='OLeary'  />
			<marker id='33' x='71.09' y='31.62' label='Nail Pond' labelPos='left'   />
			<!--<marker id='34' x='75.27' y='38.94' label='Tignish' labelPos='top'  />-->
			<marker id='35' x='51.22' y='41.03' label='Skinners Pond' labelPos='right'  />
			<marker id='36' x='42.86' y='56.71' label='Miminegash' labelPos='right'  />
		</definition>
		<application>
			<marker id='CH' shapeId='myCustomShape'  />
			<marker id='01' shapeId='newCustomShape'  />
			<marker id='02' shapeId='newCustomShape'  />
			<marker id='03' shapeId='newCustomShape'  />
			<marker id='04' shapeId='newCustomShape'  />
			<marker id='06' shapeId='newCustomShape'  />
			<marker id='07' shapeId='newCustomShape'  />
			<marker id='08' shapeId='newCustomShape'  />
			<marker id='09' shapeId='newCustomShape'  />
			<marker id='10' shapeId='newCustomShape'  />
			<marker id='11' shapeId='newCustomShape'  />
			<marker id='12' shapeId='newCustomShape'  />
			<marker id='13' shapeId='newCustomShape'  />
			<marker id='14' shapeId='newCustomShape'  />
			<marker id='16' shapeId='newCustomShape'  />
			<marker id='15' shapeId='newCustomShape'  />
			<marker id='17' shapeId='newCustomShape'  />
			<marker id='18' shapeId='newCustomShape'  />
			<marker id='19' shapeId='newCustomShape'  />
			<marker id='20' shapeId='newCustomShape'  />
			<marker id='21' shapeId='newCustomShape'  />
			<marker id='22' shapeId='newCustomShape'  />
			<marker id='23' shapeId='newCustomShape'  />
			<marker id='24' shapeId='newCustomShape'  />
			<marker id='25' shapeId='newCustomShape'  />
			<marker id='26' shapeId='newCustomShape'  />
			<marker id='27' shapeId='newCustomShape'  />
			<marker id='28' shapeId='newCustomShape'  />
			<marker id='29' shapeId='newCustomShape'  />
			<marker id='30' shapeId='newCustomShape'  />
			<marker id='31' shapeId='newCustomShapee'  />
			<marker id='32' shapeId='newCustomShape'  />
			<marker id='33' shapeId='newCustomShape'  />
			<marker id='34' shapeId='newCustomShape'  />
			<marker id='35' shapeId='newCustomShape'  />
			<marker id='36' shapeId='newCustomShape'  />
		</application>
	</markers>
</map>